{
"ANDROID":
[
{
"platformName": "Android",
"platformVersion":"8.1.0",
"automationName":"uiautomator2",
"autoLaunch":true,
"noReset":true,
"fullReset":false,
"newCommandTimeout":60,
"androidInstallTimeout":150000,
"autoDismissAlerts":true,
"appPackage":"null",
"appActivity":"null"
}
],
"IOS":
[
{
"platformName": "iOS",
"platformVersion": "12.2",
"automationName": "XCUITest",
"autoLaunch":true,
"fullReset":false,
"noReset":false,
"useNewWDA":true,
"newCommandTimeout":60,
"useJSONSource":true,
"autoDismissAlerts":true,
"bundleId":"null",
"waitForQuiescence":false,
"wdaStartupRetries":5,
"wdaStartupRetryInterval":1000
}
]
}